essnapshot/__init__.py
essnapshot/cli.py
essnapshot/es.py
essnapshot/helpers.py
essnapshot-0.1.1.dist-info/entry_points.txt
essnapshot-0.1.1.dist-info/LICENSE
essnapshot-0.1.1.dist-info/WHEEL
essnapshot-0.1.1.dist-info/METADATA
essnapshot-0.1.1.dist-info/RECORD
