Metadata-Version: 2.1
Name: essnapshot
Version: 0.1.1
Summary: Tool for Elasticsearch snapshot creation and rotation.
Home-page: https://github.com/gricertg/essnapshot
License: GPL-3.0-or-later
Author: gricertg
Author-email: gricertg@posteo.de
Requires-Python: >=3.6,<4.0
Classifier: License :: OSI Approved :: GNU General Public License v3 or later (GPLv3+)
Classifier: Programming Language :: Python :: 3
Classifier: Programming Language :: Python :: 3.10
Classifier: Programming Language :: Python :: 3.6
Classifier: Programming Language :: Python :: 3.7
Classifier: Programming Language :: Python :: 3.8
Classifier: Programming Language :: Python :: 3.9
Requires-Dist: elasticsearch (>=7.8.1,<8.0.0)
Requires-Dist: pyyaml (>=5.3.1,<6.0.0)
Project-URL: Repository, https://github.com/gricertg/essnapshot
